slax/__init__.py
slax/eval/gen_ll.py
slax/eval/jax_randman.py
slax/eval/randman_dataset.py
slax/eval/test_eval_utils.py
slax/eval/test_randman_dataset.py
slax/eval/utils.py
slax/models/neurons.py
slax/models/surrogates.py
slax/models/test_models_utils.py
slax/models/test_neurons.py
slax/models/test_surrogates.py
slax/models/utils.py
slax/train/custom_learning.py
slax/train/test_custom_learning.py
slax/train/test_train_utils.py
slax/train/utils.py
slax-0.0.1.dist-info/LICENSE
slax-0.0.1.dist-info/METADATA
slax-0.0.1.dist-info/WHEEL
slax-0.0.1.dist-info/top_level.txt
slax-0.0.1.dist-info/RECORD
